discord-stubs/__init__.pyi
discord-stubs/__main__.pyi
discord-stubs/abc.pyi
discord-stubs/activity.pyi
discord-stubs/appinfo.pyi
discord-stubs/asset.pyi
discord-stubs/audit_logs.pyi
discord-stubs/backoff.pyi
discord-stubs/calls.pyi
discord-stubs/channel.pyi
discord-stubs/client.pyi
discord-stubs/colour.pyi
discord-stubs/context_managers.pyi
discord-stubs/embeds.pyi
discord-stubs/emoji.pyi
discord-stubs/enums.pyi
discord-stubs/errors.pyi
discord-stubs/ext/commands/__init__.pyi
discord-stubs/ext/commands/_types.pyi
discord-stubs/ext/commands/bot.pyi
discord-stubs/ext/commands/cog.pyi
discord-stubs/ext/commands/context.pyi
discord-stubs/ext/commands/converter.pyi
discord-stubs/ext/commands/cooldowns.pyi
discord-stubs/ext/commands/core.pyi
discord-stubs/ext/commands/errors.pyi
discord-stubs/ext/commands/help.pyi
discord-stubs/ext/commands/view.pyi
discord-stubs/ext/tasks/__init__.pyi
discord-stubs/file.pyi
discord-stubs/flags.pyi
discord-stubs/gateway.pyi
discord-stubs/guild.pyi
discord-stubs/http.pyi
discord-stubs/integrations.pyi
discord-stubs/invite.pyi
discord-stubs/iterators.pyi
discord-stubs/member.pyi
discord-stubs/mentions.pyi
discord-stubs/message.pyi
discord-stubs/mixins.pyi
discord-stubs/object.pyi
discord-stubs/oggparse.pyi
discord-stubs/opus.pyi
discord-stubs/partial_emoji.pyi
discord-stubs/permissions.pyi
discord-stubs/player.pyi
discord-stubs/raw_models.pyi
discord-stubs/reaction.pyi
discord-stubs/relationship.pyi
discord-stubs/role.pyi
discord-stubs/shard.pyi
discord-stubs/state.pyi
discord-stubs/sticker.pyi
discord-stubs/team.pyi
discord-stubs/template.pyi
discord-stubs/user.pyi
discord-stubs/utils.pyi
discord-stubs/voice_client.pyi
discord-stubs/webhook.pyi
discord-stubs/widget.pyi
discord.py_stubs-1.7.3.dist-info/LICENSE
discord.py_stubs-1.7.3.dist-info/WHEEL
discord.py_stubs-1.7.3.dist-info/METADATA
discord.py_stubs-1.7.3.dist-info/RECORD
