Metadata-Version: 2.1
Name: discord.py-stubs
Version: 1.7.3
Summary: discord.py stubs
Home-page: https://github.com/bryanforbes/discord.py-stubs
License: BSD-3-Clause
Author: Bryan Forbes
Author-email: bryan@reigndropsfall.net
Requires-Python: >=3.6.2,<4.0.0
Classifier: Development Status :: 4 - Beta
Classifier: Intended Audience :: Developers
Classifier: License :: OSI Approved :: BSD License
Classifier: Programming Language :: Python :: 3
Classifier: Programming Language :: Python :: 3.7
Classifier: Programming Language :: Python :: 3.8
Classifier: Programming Language :: Python :: 3.9
Classifier: Typing :: Typed
Requires-Dist: discord.py (>=1.7.0,<1.8.0)
Requires-Dist: mypy (>=0.800)
Requires-Dist: typing-extensions (>=3.7.4,<4.0.0)
